{
    "version": "0.5.0",
    "description": "A collection of miscellaneous commands",
    "homepage": "https://github.com/goark/toolbox",
    "license": "Apache License 2.0",
    "architecture": {
        "64bit": {
            "url": "https://github.com/goark/toolbox/releases/download/v0.5.0/toolbox_0.5.0_Windows_64bit.zip",
            "hash": "d4a08b23a7b3bb04a50c55b030d95b854b05fd9803e66ec2e3dd12c82168071f"
        },
        "arm64": {
            "url": "https://github.com/goark/toolbox/releases/download/v0.5.0/toolbox_0.5.0_Windows_ARM64.zip",
            "hash": "f55014295ab1d710b450571f9d9105d2706f57e2e7a89f80b441005a52c093c3"
        }
    },
    "bin": [
        "toolbox.exe"
    ],
    "checkver": "github",
    "autoupdate": {
        "architecture": {
            "64bit": {
                "url": "https://github.com/goark/toolbox/releases/download/v$version/toolbox_$version_Windows_64bit.zip"
            },
            "arm64": {
                "url": "https://github.com/goark/toolbox/releases/download/v$version/toolbox_$version_Windows_ARM64.zip"
            }
        }
    }
}
